odoo/addons/stock_orderpoint_move_link/README.rst
odoo/addons/stock_orderpoint_move_link/__init__.py
odoo/addons/stock_orderpoint_move_link/__manifest__.py
odoo/addons/stock_orderpoint_move_link/i18n/fr.po
odoo/addons/stock_orderpoint_move_link/i18n/stock_orderpoint_move_link.pot
odoo/addons/stock_orderpoint_move_link/i18n/zh_CN.po
odoo/addons/stock_orderpoint_move_link/models/__init__.py
odoo/addons/stock_orderpoint_move_link/models/stock.py
odoo/addons/stock_orderpoint_move_link/models/stock_move.py
odoo/addons/stock_orderpoint_move_link/models/stock_warehouse_orderpoint.py
odoo/addons/stock_orderpoint_move_link/readme/CONTRIBUTORS.rst
odoo/addons/stock_orderpoint_move_link/readme/DESCRIPTION.rst
odoo/addons/stock_orderpoint_move_link/static/description/icon.png
odoo/addons/stock_orderpoint_move_link/static/description/index.html
odoo/addons/stock_orderpoint_move_link/tests/__init__.py
odoo/addons/stock_orderpoint_move_link/tests/test_stock_orderpoint_move_link.py
odoo/addons/stock_orderpoint_move_link/views/stock_move_views.xml
odoo12_addon_stock_orderpoint_move_link-12.0.1.1.1.dist-info/METADATA
odoo12_addon_stock_orderpoint_move_link-12.0.1.1.1.dist-info/WHEEL
odoo12_addon_stock_orderpoint_move_link-12.0.1.1.1.dist-info/top_level.txt
odoo12_addon_stock_orderpoint_move_link-12.0.1.1.1.dist-info/RECORD
